pgorm/__init__.py
pgorm/fields.py
pgorm/models.py
pgorm/postgresql.py
pgorm-0.0.1.dist-info/LICENSE
pgorm-0.0.1.dist-info/METADATA
pgorm-0.0.1.dist-info/WHEEL
pgorm-0.0.1.dist-info/top_level.txt
pgorm-0.0.1.dist-info/RECORD
